{
  "checkpoint_id": "cp_b624fce7",
  "workflow_id": "event_verify",
  "step_id": "s2",
  "timestamp": "2026-04-17T13:04:11.794042",
  "state": {
    "instance_id": "inst_2b19a758ae2f",
    "step_input": {
      "context": {},
      "dependencies": {},
      "params": {}
    },
    "step_results": {
      "s1": {
        "step_id": "s1",
        "status": "completed",
        "started_at": "2026-04-17T13:04:11.791445",
        "completed_at": "2026-04-17T13:04:11.792725",
        "output": {
          "step1": "done"
        },
        "error": null,
        "retry_count": 0,
        "duration_ms": 1,
        "fallback_used": false,
        "rollback_used": false,
        "checkpoint_id": "cp_382bb78f",
        "rollback_point_id": "rb_c896561e",
        "fallback_decision": null
      }
    }
  },
  "completed_steps": [
    "s1"
  ],
  "pending_steps": [
    "s2"
  ],
  "metadata": {
    "phase": "before_step",
    "attempt": 0
  }
}