{
  "profile": "nightly",
  "scope": "all",
  "verified_at": "2026-04-12T19:53:56.437517",
  "overall_passed": true,
  "failure_reasons": [],
  "p0_count": 0,
  "p1_count": 0,
  "p2_count": 33,
  "local_status": "pass",
  "local_results": [
    {
      "skill": "docx",
      "status": "pass",
      "message": ""
    },
    {
      "skill": "cron",
      "status": "pass",
      "message": ""
    },
    {
      "skill": "pdf",
      "status": "pass",
      "message": ""
    }
  ],
  "integration_status": "pass",
  "integration_results": [
    {
      "skill": "file-manager",
      "status": "pass",
      "message": ""
    }
  ],
  "external_status": "pass",
  "external_results": [
    {
      "skill": "find-skills",
      "status": "skipped",
      "message": "缺少: ['SKILLHUB_TOKEN']"
    },
    {
      "skill": "huawei-drive",
      "status": "skipped",
      "message": "缺少: ['HUAWEI_DRIVE_TOKEN']"
    },
    {
      "skill": "xiaoyi-image-understanding",
      "status": "skipped",
      "message": "缺少: ['XIAOYI_TOKEN']"
    }
  ],
  "skipped_skills": [
    {
      "skill": "find-skills",
      "status": "skipped",
      "message": "缺少: ['SKILLHUB_TOKEN']"
    },
    {
      "skill": "huawei-drive",
      "status": "skipped",
      "message": "缺少: ['HUAWEI_DRIVE_TOKEN']"
    },
    {
      "skill": "xiaoyi-image-understanding",
      "status": "skipped",
      "message": "缺少: ['XIAOYI_TOKEN']"
    }
  ]
}