{
  "states": {
    "fusion_engine": {
      "last_refreshed": "2026-04-21T12:17:34.162567",
      "refresh_count": 41
    },
    "memory_engine": {
      "last_refreshed": "2026-04-21T12:02:31.912439",
      "refresh_count": 40
    },
    "rule_engine": {
      "last_refreshed": "2026-04-21T12:02:31.913419",
      "refresh_count": 40
    },
    "exception_manager": {
      "last_refreshed": "2026-04-21T12:02:33.715353",
      "refresh_count": 40
    },
    "dependency_manager": {
      "last_refreshed": "2026-04-21T12:02:33.716163",
      "refresh_count": 40
    },
    "delete_manager": {
      "last_refreshed": "2026-04-21T12:02:33.716922",
      "refresh_count": 40
    },
    "skill_registry": {
      "last_refreshed": "2026-04-21T12:02:33.717624",
      "refresh_count": 40
    },
    "core_identity": {
      "last_refreshed": "2026-04-21T12:02:33.718413",
      "refresh_count": 40
    },
    "architecture": {
      "last_refreshed": "2026-04-21T12:02:33.719733",
      "refresh_count": 40
    }
  },
  "last_check": null,
  "version": "1.0.0"
}