{
  "states": {
    "fusion_engine": {
      "last_refreshed": "2026-04-19T14:59:35.970563",
      "refresh_count": 26
    },
    "memory_engine": {
      "last_refreshed": "2026-04-19T14:43:24.190593",
      "refresh_count": 25
    },
    "rule_engine": {
      "last_refreshed": "2026-04-19T14:43:24.191459",
      "refresh_count": 25
    },
    "exception_manager": {
      "last_refreshed": "2026-04-19T14:43:26.003467",
      "refresh_count": 25
    },
    "dependency_manager": {
      "last_refreshed": "2026-04-19T14:43:26.004202",
      "refresh_count": 25
    },
    "delete_manager": {
      "last_refreshed": "2026-04-19T14:43:26.004883",
      "refresh_count": 25
    },
    "skill_registry": {
      "last_refreshed": "2026-04-19T14:43:26.005525",
      "refresh_count": 25
    },
    "core_identity": {
      "last_refreshed": "2026-04-19T14:43:26.006806",
      "refresh_count": 25
    },
    "architecture": {
      "last_refreshed": "2026-04-19T14:43:26.007889",
      "refresh_count": 25
    }
  },
  "last_check": "2026-04-15T00:24:34.807578",
  "version": "1.0.0",
  "summary": {
    "healthy": 9,
    "unhealthy": 0,
    "critical_issues": 0
  }
}